tursopy/__init__.py
tursopy/dataclasses.py
tursopy/db.py
tursopy/endpoints.py
tursopy/exceptions.py
tursopy/tursopy.py
tursopy-0.0.3.dist-info/LICENSE
tursopy-0.0.3.dist-info/METADATA
tursopy-0.0.3.dist-info/WHEEL
tursopy-0.0.3.dist-info/top_level.txt
tursopy-0.0.3.dist-info/RECORD
