Metadata-Version: 2.1
Name: tursopy
Version: 0.0.3
Summary: Fully type-hinted Turso Platform API wrapper for Python. 
Author-email: Maurice Künicke <m.kuenicke1995@gmail.com>
Project-URL: Homepage, https://github.com/MauriceKuenicke/tursopy
Project-URL: Issues, https://github.com/MauriceKuenicke/tursopy/issues
Classifier: Programming Language :: Python :: 3
Classifier: License :: OSI Approved :: MIT License
Classifier: Operating System :: OS Independent
Requires-Python: >=3.8
License-File: LICENSE
Requires-Dist: requests
